<?xml version="1.0" encoding="utf-8"?>
<Patch>
  <Operation Class="PatchOperationFindMod">
    <mods>
      <li>[RH2] Rimmu-Nation² - Clothing</li>
    </mods>
    <match Class="PatchOperationSequence">
      <operations>
        <li Class="PatchOperationConditional">
          <xpath>Defs/ThingDef[defName="RNApparel_NorweiganShirt_Pullover"]/statBases</xpath>
          <nomatch Class="PatchOperationAdd">
            <xpath>Defs/ThingDef[defName="RNApparel_NorweiganShirt_Pullover"]</xpath>
            <value>
              <statBases />
            </value>
          </nomatch>
        </li>
        <li Class="PatchOperationReplace">
          <xpath>Defs/ThingDef[defName="RNApparel_NorweiganShirt_Pullover"]/statBases</xpath>
          <value>
            <statBases>
              <MaxHitPoints>150</MaxHitPoints>
              <Flammability>1</Flammability>
              <DeteriorationRate>2</DeteriorationRate>
              <Beauty>-3</Beauty>
              <WorkToMake>9500</WorkToMake>
              <Mass>1.6</Mass>
              <StuffEffectMultiplierArmor>1.25</StuffEffectMultiplierArmor>
              <Bulk>1</Bulk>
              <StuffEffectMultiplierInsulation_Cold>1.25</StuffEffectMultiplierInsulation_Cold>
              <StuffEffectMultiplierInsulation_Heat>0.4</StuffEffectMultiplierInsulation_Heat>
              <EquipDelay>1.5</EquipDelay>
            </statBases>
          </value>
        </li>
        <li Class="PatchOperationAddModExtension">
          <xpath>Defs/ThingDef[defName="RNApparel_NorweiganShirt_Pullover"]</xpath>
          <value>
            <li Class="CombatExtended.PartialArmorExt">
              <stats />
            </li>
          </value>
        </li>
        <li Class="PatchOperationConditional">
          <xpath>Defs/ThingDef[defName="RNApparel_NorweiganShirt_Pullover"]/apparel</xpath>
          <nomatch Class="PatchOperationAdd">
            <xpath>Defs/ThingDef[defName="RNApparel_NorweiganShirt_Pullover"]</xpath>
            <value>
              <apparel />
            </value>
          </nomatch>
        </li>
        <li Class="PatchOperationConditional">
          <xpath>Defs/ThingDef[defName="RNApparel_NorweiganShirt_Pullover"]/apparel/bodyPartGroups</xpath>
          <nomatch Class="PatchOperationAdd">
            <xpath>Defs/ThingDef[defName="RNApparel_NorweiganShirt_Pullover"]/apparel</xpath>
            <value>
              <bodyPartGroups />
            </value>
          </nomatch>
        </li>
        <li Class="PatchOperationReplace">
          <xpath>Defs/ThingDef[defName="RNApparel_NorweiganShirt_Pullover"]/apparel/bodyPartGroups</xpath>
          <value>
            <bodyPartGroups>
              <li>Neck</li>
              <li>Shoulders</li>
              <li>Arms</li>
              <li>UpperChest</li>
              <li>Waist</li>
            </bodyPartGroups>
          </value>
        </li>
      </operations>
    </match>
  </Operation>
</Patch>